typer_cli/__init__.py
typer_cli/__main__.py
typer_cli/main.py
typer_cli_forked-0.0.15.dist-info/entry_points.txt
typer_cli_forked-0.0.15.dist-info/LICENSE
typer_cli_forked-0.0.15.dist-info/WHEEL
typer_cli_forked-0.0.15.dist-info/METADATA
typer_cli_forked-0.0.15.dist-info/RECORD
