Metadata-Version: 2.1
Name: typer-cli-forked
Version: 0.0.15
Summary: Run Typer scripts with completion, without having to create a package, using Typer CLI.
Author-email: Sebastián Ramírez <tiangolo@gmail.com>
Requires-Python: >=3.7
Classifier: Environment :: Console
Classifier: Intended Audience :: Developers
Classifier: Intended Audience :: Education
Classifier: Intended Audience :: End Users/Desktop
Classifier: Intended Audience :: Information Technology
Classifier: Intended Audience :: System Administrators
Classifier: Operating System :: OS Independent
Classifier: Programming Language :: Python
Classifier: Programming Language :: Python :: 3
Classifier: Programming Language :: Python :: 3 :: Only
Classifier: Programming Language :: Python :: 3.7
Classifier: Programming Language :: Python :: 3.8
Classifier: Programming Language :: Python :: 3.9
Classifier: Programming Language :: Python :: 3.10
Classifier: Programming Language :: Python :: 3.11
Classifier: Topic :: Software Development :: Libraries :: Application Frameworks
Classifier: Topic :: Software Development :: Libraries :: Python Modules
Classifier: Topic :: Software Development :: Libraries
Classifier: Topic :: Software Development
Classifier: Topic :: Terminals
Classifier: Topic :: Utilities
Classifier: Typing :: Typed
Classifier: Development Status :: 4 - Beta
Classifier: License :: OSI Approved :: MIT License
Requires-Dist: typer ~= 0.12
Requires-Dist: colorama >=0.4.3,<=0.5.0
Requires-Dist: shellingham >= 1.3
Requires-Dist: flit ~= 3.9 ; extra == "build"
Project-URL: Documentation, https://typer.tiangolo.com/typer-cli/
Project-URL: Homepage, https://github.com/tiangolo/typer-cli
Provides-Extra: build
